NiceCSV/__init__.py
NiceCSV-1.0.0.dist-info/METADATA
NiceCSV-1.0.0.dist-info/WHEEL
NiceCSV-1.0.0.dist-info/top_level.txt
NiceCSV-1.0.0.dist-info/RECORD
