Metadata-Version: 2.1
Name: NiceCSV
Version: 1.0.0
Summary: A better alternative for csv module in python
Home-page: https://github.com/yar-go/NiceCSV
Author: Yarik Khaluza
Author-email: khaluza225@gmail.com
License: UNKNOWN
Platform: UNKNOWN
Classifier: Programming Language :: Python :: 3.7
Classifier: License :: OSI Approved :: MIT License
Classifier: Operating System :: OS Independent
Requires-Python: >=3.6
